jsonrpc/__init__.py
jsonrpc/base.py
jsonrpc/dispatcher.py
jsonrpc/exceptions.py
jsonrpc/jsonrpc.py
jsonrpc/jsonrpc1.py
jsonrpc/jsonrpc2.py
jsonrpc/manager.py
jsonrpc/six.py
jsonrpc/utils.py
jsonrpc/backend/__init__.py
jsonrpc/backend/django.py
jsonrpc/backend/flask.py
jsonrpc/tests/__init__.py
jsonrpc/tests/py35_utils.py
jsonrpc/tests/test_base.py
jsonrpc/tests/test_bug29.py
jsonrpc/tests/test_dispatcher.py
jsonrpc/tests/test_examples20.py
jsonrpc/tests/test_jsonrpc.py
jsonrpc/tests/test_jsonrpc1.py
jsonrpc/tests/test_jsonrpc2.py
jsonrpc/tests/test_jsonrpc_errors.py
jsonrpc/tests/test_manager.py
jsonrpc/tests/test_pep3107.py
jsonrpc/tests/test_utils.py
jsonrpc/tests/test_backend_django/__init__.py
jsonrpc/tests/test_backend_django/settings.py
jsonrpc/tests/test_backend_django/tests.py
jsonrpc/tests/test_backend_django/urls.py
jsonrpc/tests/test_backend_flask/__init__.py
jsonrpc/tests/test_backend_flask/tests.py
json_rpc-1.12.2.dist-info/LICENSE.txt
json_rpc-1.12.2.dist-info/METADATA
json_rpc-1.12.2.dist-info/WHEEL
json_rpc-1.12.2.dist-info/top_level.txt
json_rpc-1.12.2.dist-info/RECORD
